dgsolvdb/__init__.py
dgsolvdb/dgsolvdb.py
dgsolvdb-0.0.0a0.dist-info/LICENSE
dgsolvdb-0.0.0a0.dist-info/METADATA
dgsolvdb-0.0.0a0.dist-info/WHEEL
dgsolvdb-0.0.0a0.dist-info/top_level.txt
dgsolvdb-0.0.0a0.dist-info/RECORD
