Metadata-Version: 2.1
Name: dgsolvdb
Version: 0.0.0a0
Summary: Free energy of solvation database wrapper - no dependencies.
Author: Jackosn Burns
License: MIT
Project-URL: Homepage, https://github.com/QuantumPioneer/dgsolvdb
Classifier: Programming Language :: Python :: 3
Requires-Python: >=3.8
License-File: LICENSE
Provides-Extra: demos
Requires-Dist: jupyter ; extra == 'demos'
Provides-Extra: dev
Requires-Dist: black ; extra == 'dev'
Requires-Dist: isort ; extra == 'dev'
Requires-Dist: pytest ; extra == 'dev'
